{"nodes": [{"id": "home_user_openclaw_workspace_wiki_sources_obsidian_md_md", "label": "obsidian-md.md", "file_type": "document", "source_file": "/home/user/.openclaw/workspace/wiki/sources/obsidian-md.md", "source_location": "L1"}, {"id": "sources_obsidian_md_obsidian_md", "label": "Obsidian.md", "file_type": "document", "source_file": "/home/user/.openclaw/workspace/wiki/sources/obsidian-md.md", "source_location": "L9"}, {"id": "sources_obsidian_md_why_agent_friendly", "label": "Why Agent-Friendly", "file_type": "document", "source_file": "/home/user/.openclaw/workspace/wiki/sources/obsidian-md.md", "source_location": "L13"}, {"id": "sources_obsidian_md_ai_integrations", "label": "AI Integrations", "file_type": "document", "source_file": "/home/user/.openclaw/workspace/wiki/sources/obsidian-md.md", "source_location": "L19"}, {"id": "sources_obsidian_md_see_also", "label": "See Also", "file_type": "document", "source_file": "/home/user/.openclaw/workspace/wiki/sources/obsidian-md.md", "source_location": "L24"}], "edges": [{"source": "home_user_openclaw_workspace_wiki_sources_obsidian_md_md", "target": "sources_obsidian_md_obsidian_md", "relation": "contains", "confidence": "EXTRACTED", "source_file": "/home/user/.openclaw/workspace/wiki/sources/obsidian-md.md", "source_location": "L9", "weight": 1.0}, {"source": "sources_obsidian_md_obsidian_md", "target": "sources_obsidian_md_why_agent_friendly", "relation": "contains", "confidence": "EXTRACTED", "source_file": "/home/user/.openclaw/workspace/wiki/sources/obsidian-md.md", "source_location": "L13", "weight": 1.0}, {"source": "sources_obsidian_md_obsidian_md", "target": "sources_obsidian_md_ai_integrations", "relation": "contains", "confidence": "EXTRACTED", "source_file": "/home/user/.openclaw/workspace/wiki/sources/obsidian-md.md", "source_location": "L19", "weight": 1.0}, {"source": "sources_obsidian_md_obsidian_md", "target": "sources_obsidian_md_see_also", "relation": "contains", "confidence": "EXTRACTED", "source_file": "/home/user/.openclaw/workspace/wiki/sources/obsidian-md.md", "source_location": "L24", "weight": 1.0}], "input_tokens": 0, "output_tokens": 0}